[
  {
    "1": "Apa yang dimaksud dengan Masa Pra-Sejarah?",
    "2": "Berapa rentang waktu Masa Pra-Sejarah?",
    "3": "Apa yang menjadi ciri utama manusia pada Masa Pra-Sejarah?",
    "4": "Apa kehidupan sosial masyarakat pada Masa Pra-Sejarah?",
    "5": "Bagaimana manusia Masa Pra-Sejarah memenuhi kebutuhan hidupnya?",
    "6": "Apa peran alat-alat batu pada Masa Pra-Sejarah?",
    "7": "Apa yang menjadi kepercayaan manusia Masa Pra-Sejarah terhadap alam?",
    "8": "Apakah manusia Masa Pra-Sejarah sudah mengenal pertanian?",
    "9": "Bagaimana manusia Masa Pra-Sejarah berkomunikasi?",
    "10": "Apa yang menjadi seni dan keterampilan manusia Masa Pra-Sejarah?",
    "11": "Bagaimana manusia Masa Pra-Sejarah membuat dan menggunakan peralatan dari logam?",
    "12": "Apa yang menjadi dampak perubahan iklim terhadap kehidupan manusia Masa Pra-Sejarah?",
    "13": "Apakah manusia Masa Pra-Sejarah sudah mengenal sistem penulisan?",
    "14": "Apa yang menjadi alat transportasi utama manusia Masa Pra-Sejarah?",
    "15": "Bagaimana sistem pemukiman manusia Masa Pra-Sejarah?",
    "16": "Apakah manusia Masa Pra-Sejarah sudah memiliki sistem perdagangan?",
    "17": "Apa yang menjadi hewan peliharaan manusia Masa Pra-Sejarah?",
    "18": "Apa yang menjadi kegiatan seni rupa pada Masa Pra-Sejarah?",
    "19": "Bagaimana pola kehidupan sosial dan keluarga manusia Masa Pra-Sejarah?",
    "20": "Apakah manusia Masa Pra-Sejarah sudah mengenal konsep agama?"
  },
  {
    "1": { "a": "Sejarah yang ditulis oleh manusia", "b": "Sejarah yang terjadi sebelum penulisan sejarah", "c": "Sejarah yang berkaitan dengan periode tertentu", "d": "Sejarah yang terjadi setelah penulisan sejarah" },
    "2": { "a": "1000 tahun", "b": "5000 tahun", "c": "10.000 tahun", "d": "20.000 tahun" },
    "3": { "a": "Penggunaan alat tulis", "b": "Kemampuan berbicara", "c": "Pertanian", "d": "Penggunaan teknologi" },
    "4": { "a": "Nomaden", "b": "Sedentaris", "c": "Penduduk perkotaan", "d": "Pertanian intensif" },
    "5": { "a": "Berburu dan meramu", "b": "Berkebun", "c": "Pertanian", "d": "Berdagang" },
    "6": { "a": "Alat pertanian", "b": "Alat musik", "c": "Alat transportasi", "d": "Alat-alat untuk keperluan sehari-hari" },
    "7": { "a": "Animisme", "b": "Monotheisme", "c": "Polytheisme", "d": "Atheisme" },
    "8": { "a": "Ya", "b": "Tidak", "c": "Sebagian", "d": "Tidak dapat dipastikan" },
    "9": { "a": "Menggunakan tulisan", "b": "Menggunakan isyarat tubuh", "c": "Menggunakan seni lukis", "d": "Menggunakan bahasa lisan" },
    "10": { "a": "Seni lukis di gua", "b": "Seni ukir pada batu", "c": "Seni musik", "d": "Keterampilan membuat perhiasan" },
    "11": { "a": "Pengolahan besi", "b": "Pengolahan emas", "c": "Pengolahan perunggu", "d": "Pengolahan timah" },
    "12": { "a": "Peningkatan produksi pertanian", "b": "Perubahan pola migrasi", "c": "Penurunan tingkat pengangguran", "d": "Penyusutan sumber daya alam" },
    "13": { "a": "Sudah", "b": "Belum", "c": "Hanya gambar-gambar", "d": "Peninggalan tulisan ditemukan" },
    "14": { "a": "Kereta kuda", "b": "Perahu kayu", "c": "Sepeda", "d": "Kendaraan bermotor primitif" },
    "15": { "a": "Pemukiman permanen", "b": "Pemukiman sementara", "c": "Pemukiman terapung", "d": "Pemukiman bergantian" },
    "16": { "a": "Sudah memiliki mata uang", "b": "Sistem barter", "c": "Perdagangan langsung", "d": "Belum mengenal perdagangan" },
    "17": { "a": "Anjing", "b": "Kuda", "c": "Gajah", "d": "Babi" },
    "18": { "a": "Seni ukir pada batu", "b": "Seni ukir pada tulang", "c": "Seni melukis di dinding gua", "d": "Seni membuat patung dari tanah liat" },
    "19": { "a": "Matriarki", "b": "Patriarki", "c": "Sistem kekeluargaan eksogami", "d": "Komunalisme" },
    "20": { "a": "Sudah memiliki sistem kepercayaan", "b": "Masih bersifat animisme", "c": "Hanya kepercayaan pada alam", "d": "Belum memiliki kepercayaan agama" }
  },
  {
    "1": "Sejarah yang terjadi sebelum penulisan sejarah",
    "2": "10.000 tahun",
    "3": "Kemampuan berbicara",
    "4": "Nomaden",
    "5": "Berburu dan meramu",
    "6": "Alat-alat untuk keperluan sehari-hari",
    "7": "Animisme",
    "8": "Ya",
    "9": "Menggunakan bahasa lisan",
    "10": "Keterampilan membuat perhiasan",
    "11": "Pengolahan perunggu",
    "12": "Perubahan pola migrasi",
    "13": "Belum",
    "14": "Perahu kayu",
    "15": "Pemukiman permanen",
    "16": "Sistem barter",
    "17": "Gajah",
    "18": "Seni melukis di dinding gua",
    "19": "Patriarki",
    "20": "Sudah memiliki sistem kepercayaan"
  }
]
